{
  "cards": [
		{
			"mdFile": "/images/etc_study/4/4.md",
      "image": "/images/etc_study/4/main_image.webp",
			"sortDate": "2024-11-10",
      "title": "인터넷(Internet) 동작 원리",
			"subTitle": "인터넷(Internet)은 프로토콜 스위트(TCP/IP)를 기반으로 하여 전 세계적으로 연결되어있는 컴퓨터 네트워크 통신망을 일컫는 말이다.",
			"hashs": [
				{"name": "#Internet"}
      ]
    },
		{
			"mdFile": "/images/etc_study/3/3.md",
      "image": "/images/etc_study/3/main_image.webp",
			"sortDate": "2024-10-15",
      "title": "Docker란 무엇인가…에 대한 고찰",
			"subTitle": "Docker는 간단한 명령어로 컨테이너 이미지를 생성하고 저장할 수 있는 서버 가상화 플랫폼입니다. Docker Container는 가상화 기술 중 하나로 기존 가상화와 달리 프로세스를 격리시켜 동작하는 방식을 말합니다.",
			"hashs": [
				{"name": "#Docker"}
      ]
    },
		{
			"mdFile": "/images/etc_study/2/2.md",
      "image": "/images/etc_study/2/main_image.webp",
			"sortDate": "2024-09-15",
      "title": "Github Pages로 정적파일 자동 배포하기",
			"subTitle": "gh-pages는 Node.js 환경에서 사용되는 npm 패키지입니다. 로컬에서 사이트를 빌드하고, 빌드된 정적 파일을 GitHub Pages에 쉽게 배포가 가능해집니다. gh-pages는 빌드된 정적 사이트를 자동으로 gh-pages 브랜치에 푸시하게 해줍니다.",
			"hashs": [
				{"name": "#Github"}
      ]
    },
		{
			"mdFile": "/images/etc_study/1/1.md",
      "image": "/images/etc_study/1/main_image.webp",
			"sortDate": "2024-08-15",
      "title": "Github SSH 연결하기",
			"subTitle": "SSH(Secure Shell)는 GitHub Repositories에 데이터를 전송할 때 보안 통신을 위해 사용되는 프로토콜입니다. SSH는 데이터 전송 중에 암호화를 사용하여 보안을 유지할 수 있다는 장점이 있습니다.",
			"hashs": [
				{"name": "#Github"},
				{"name": "#SSH"}
      ]
    }
  ]
}